{
    "mipEra": "cmip6", 
    "institute": "inpe", 
    "seedingSource": "Spreadsheet", 
    "sourceID": "besm-2-9", 
    "topic": "atmos", 
    "content": {
        "cmip6.atmos.key_properties.name": {
            "values": [
                "Brazilian Atmospheric Model"
            ]
        }, 
        "cmip6.atmos.key_properties.keywords": {
            "values": [
                "BAM"
            ]
        }, 
        "cmip6.atmos.key_properties.resolution.horizontal_resolution_name": {
            "values": [
                "T126L42"
            ]
        }, 
        "cmip6.atmos.key_properties.resolution.number_of_vertical_levels": {
            "values": [
                42
            ]
        }, 
        "cmip6.atmos.key_properties.resolution.high_top": {
            "values": [
                true
            ]
        }, 
        "cmip6.atmos.grid.overview": {
            "values": [
                "spectra horizontal grid and sigma vertical levelsl"
            ]
        }, 
        "cmip6.atmos.grid.discretisation.horizontal.scheme_type": {
            "values": [
                "spectral"
            ]
        }, 
        "cmip6.atmos.grid.discretisation.horizontal.scheme_method": {
            "values": [
                "finite difference"
            ]
        }, 
        "cmip6.atmos.grid.discretisation.horizontal.scheme_order": {
            "values": [
                "second"
            ]
        }, 
        "cmip6.atmos.grid.discretisation.horizontal.horizontal_pole": {
            "values": [
                "filter"
            ]
        }, 
        "cmip6.atmos.grid.discretisation.horizontal.grid_type": {
            "values": [
                "Gaussian"
            ]
        }, 
        "cmip6.atmos.dynamical_core.name": {
            "values": [
                "espectral dynamics core"
            ]
        }, 
        "cmip6.atmos.dynamical_core.timestepping_type": {
            "values": [
                "semi-implicit"
            ]
        }, 
        "cmip6.atmos.dynamical_core.prognostic_variables": {
            "values": [
                "surface pressure", 
                "wind components", 
                "divergence/curl", 
                "temperature", 
                "potential temperature", 
                "total water", 
                "water vapour", 
                "water ice"
            ]
        }, 
        "cmip6.atmos.dynamical_core.top_boundary.top_boundary_condition": {
            "values": [
                "radiation boundary condition"
            ]
        }, 
        "cmip6.atmos.dynamical_core.top_boundary.top_heat": {
            "values": [
                "Radiative"
            ]
        }, 
        "cmip6.atmos.dynamical_core.top_boundary.top_wind": {
            "values": [
                "High pass filter"
            ]
        }, 
        "cmip6.atmos.dynamical_core.diffusion_horizontal.scheme_name": {
            "values": [
                "fourth order horizontal linear diffusion"
            ]
        }, 
        "cmip6.atmos.dynamical_core.diffusion_horizontal.scheme_method": {
            "values": [
                "iterated Laplacian"
            ]
        }, 
        "cmip6.atmos.dynamical_core.advection.tracers.scheme_name": {
            "values": [
                "Other: Ritchie and Harold (1987)"
            ]
        }, 
        "cmip6.atmos.dynamical_core.advection.tracers.scheme_characteristics": {
            "values": [
                "semi-Lagrangian"
            ]
        }, 
        "cmip6.atmos.dynamical_core.advection.tracers.conserved_quantities": {
            "values": [
                "tracer mass"
            ]
        }, 
        "cmip6.atmos.dynamical_core.advection.tracers.conservation_method": {
            "values": [
                "conservation fixer"
            ]
        }, 
        "cmip6.atmos.dynamical_core.advection.momentum.scheme_characteristics": {
            "values": [
                "2nd order"
            ]
        }, 
        "cmip6.atmos.dynamical_core.advection.momentum.scheme_staggering_type": {
            "values": [
                "Arakawa B-grid"
            ]
        }, 
        "cmip6.atmos.dynamical_core.advection.momentum.conserved_quantities": {
            "values": [
                "Mass"
            ]
        }, 
        "cmip6.atmos.radiation.name": {
            "values": [
                "radiation"
            ]
        }, 
        "cmip6.atmos.radiation.aerosols": {
            "values": [
                "BC: black carbon / soot"
            ]
        }, 
        "cmip6.atmos.radiation.shortwave_radiation.name": {
            "values": [
                "Clirad-Tarasova"
            ]
        }, 
        "cmip6.atmos.radiation.shortwave_radiation.spectral_integration": {
            "values": [
                "correlated-k"
            ]
        }, 
        "cmip6.atmos.radiation.shortwave_radiation.transport_calculation": {
            "values": [
                "two-stream"
            ]
        }, 
        "cmip6.atmos.radiation.shortwave_radiation.spectral_intervals": {
            "values": [
                8
            ]
        }, 
        "cmip6.atmos.radiation.shortwave_radiation.general_interactions": {
            "values": [
                "scattering"
            ]
        }, 
        "cmip6.atmos.radiation.shortwave_GHG.greenhouse_gas_complexity": {
            "values": [
                "CO2: Carbon Dioxide", 
                "O3", 
                "H2O", 
                "Other: O2"
            ]
        }, 
        "cmip6.atmos.radiation.shortwave_cloud_ice.physical_representation": {
            "values": [
                "effective crystal radius"
            ]
        }, 
        "cmip6.atmos.radiation.shortwave_cloud_ice.optical_methods": {
            "values": [
                "geometric optics: For non-spherical particles"
            ]
        }, 
        "cmip6.atmos.radiation.shortwave_cloud_liquid.physical_representation": {
            "values": [
                "effective cloud droplet radii", 
                "liquid water path: Integrated liquid water path through the cloud kg m-2"
            ]
        }, 
        "cmip6.atmos.radiation.shortwave_cloud_liquid.optical_methods": {
            "values": [
                "geometric optics: For non-spherical particles"
            ]
        }, 
        "cmip6.atmos.radiation.shortwave_cloud_inhomogeneity.cloud_inhomogeneity": {
            "values": [
                "analytic"
            ]
        }, 
        "cmip6.atmos.radiation.shortwave_aerosols.physical_representation": {
            "values": [
                "effective radii", 
                "asymmetry", 
                "aspect ratio"
            ]
        }, 
        "cmip6.atmos.radiation.shortwave_aerosols.optical_methods": {
            "values": [
                "geometric optics: For non-spherical particles"
            ]
        }, 
        "cmip6.atmos.radiation.longwave_radiation.name": {
            "values": [
                "Clirad-TF"
            ]
        }, 
        "cmip6.atmos.radiation.longwave_radiation.spectral_integration": {
            "values": [
                "wide-band model"
            ]
        }, 
        "cmip6.atmos.radiation.longwave_radiation.transport_calculation": {
            "values": [
                "two-stream"
            ]
        }, 
        "cmip6.atmos.radiation.longwave_radiation.spectral_intervals": {
            "values": [
                12
            ]
        }, 
        "cmip6.atmos.radiation.longwave_radiation.general_interactions": {
            "values": [
                "emission/absorption,", 
                "scattering"
            ]
        }, 
        "cmip6.atmos.radiation.longwave_GHG.greenhouse_gas_complexity": {
            "values": [
                "CO2: Carbon Dioxide", 
                "CH4: Methane", 
                "N2O: Nitrous Oxide", 
                "CFC-11 eq: Summarize the effect of non CO2, CH4, N2O and CFC-12 gases with an equivalence concentration of CFC-11", 
                "H2O", 
                "CFC-12 eq: Summarize the radiative effect of the Ozone Depleating Substances, ODSs, with a CFC-12 equivalence concentration", 
                "O3"
            ]
        }, 
        "cmip6.atmos.radiation.longwave_GHG.ODS": {
            "values": [
                "CFC-12: CFC", 
                "CFC-11: CFC"
            ]
        }, 
        "cmip6.atmos.radiation.longwave_cloud_ice.physical_reprenstation": {
            "values": [
                "effective crystal radius", 
                "crystal asymmetry", 
                "ice water path: Integrated ice water path through the cloud kg m-2"
            ]
        }, 
        "cmip6.atmos.radiation.longwave_cloud_ice.optical_methods": {
            "values": [
                "geometric optics: For non-spherical particles"
            ]
        }, 
        "cmip6.atmos.radiation.longwave_cloud_liquid.physical_representation": {
            "values": [
                "effective cloud droplet radii", 
                "liquid water path: Integrated liquid water path through the cloud kg m-2"
            ]
        }, 
        "cmip6.atmos.radiation.longwave_cloud_liquid.optical_methods": {
            "values": [
                "geometric optics: For non-spherical particles"
            ]
        }, 
        "cmip6.atmos.radiation.longwave_cloud_inhomogeneity.cloud_inhomogeneity": {
            "values": [
                "analytic"
            ]
        }, 
        "cmip6.atmos.radiation.longwave_aerosols.physical_representation": {
            "values": [
                "effective radii", 
                "asymmetry", 
                "aspect ratio"
            ]
        }, 
        "cmip6.atmos.turbulence_convection.name": {
            "values": [
                "Bretherton and Park (2008)"
            ]
        }, 
        "cmip6.atmos.turbulence_convection.boundary_layer_turbulence.scheme_name": {
            "values": [
                "Other: Bretherton and Park (2008)"
            ]
        }, 
        "cmip6.atmos.turbulence_convection.boundary_layer_turbulence.scheme_type": {
            "values": [
                "non-local diffusion", 
                "Monin-Obukhov similarity", 
                "TKE coupled with water"
            ]
        }, 
        "cmip6.atmos.turbulence_convection.boundary_layer_turbulence.closure_order": {
            "values": [
                4
            ]
        }, 
        "cmip6.atmos.turbulence_convection.boundary_layer_turbulence.counter_gradient": {
            "values": [
                true
            ]
        }, 
        "cmip6.atmos.turbulence_convection.deep_convection.scheme_name": {
            "values": [
                "Simplified Arakawa"
            ]
        }, 
        "cmip6.atmos.turbulence_convection.deep_convection.scheme_type": {
            "values": [
                "mass-flux"
            ]
        }, 
        "cmip6.atmos.turbulence_convection.deep_convection.scheme_method": {
            "values": [
                "CAPE: Mass flux determined by CAPE, convectively available potential energy."
            ]
        }, 
        "cmip6.atmos.turbulence_convection.deep_convection.processes": {
            "values": [
                "vertical momentum transport", 
                "convective momentum transport", 
                "entrainment", 
                "detrainment", 
                "updrafts", 
                "downdrafts", 
                "re-evaporation of convective precipitation"
            ]
        }, 
        "cmip6.atmos.turbulence_convection.deep_convection.microphysics": {
            "values": [
                "two moment"
            ]
        }, 
        "cmip6.atmos.turbulence_convection.shallow_convection.scheme_name": {
            "values": [
                "Tiedtke"
            ]
        }, 
        "cmip6.atmos.turbulence_convection.shallow_convection.scheme_type": {
            "values": [
                "cumulus-capped boundary layer"
            ]
        }, 
        "cmip6.atmos.turbulence_convection.shallow_convection.scheme_method": {
            "values": [
                "separate diagnosis: Deep and Shallow convection schemes use different thermodynamic closure criteria"
            ]
        }, 
        "cmip6.atmos.turbulence_convection.shallow_convection.processes": {
            "values": [
                "entrainment", 
                "detrainment"
            ]
        }, 
        "cmip6.atmos.microphysics_precipitation.name": {
            "values": [
                "Morrison"
            ]
        }, 
        "cmip6.atmos.microphysics_precipitation.large_scale_precipitation.scheme_name": {
            "values": [
                "Large Scale Precipitation"
            ]
        }, 
        "cmip6.atmos.microphysics_precipitation.large_scale_precipitation.hydrometeors": {
            "values": [
                "liquid rain", 
                "snow", 
                "hail", 
                "graupel"
            ]
        }, 
        "cmip6.atmos.microphysics_precipitation.large_scale_cloud_microphysics.scheme_name": {
            "values": [
                "Morrison"
            ]
        }, 
        "cmip6.atmos.cloud_scheme.scheme_type": {
            "values": [
                "diagnostic"
            ]
        }, 
        "cmip6.atmos.cloud_scheme.uses_separate_treatment": {
            "values": [
                "diagnostic but separeted in convective, stratiform and boundary layer clouds"
            ]
        }, 
        "cmip6.atmos.cloud_scheme.processes": {
            "values": [
                "bulk cloud"
            ]
        }, 
        "cmip6.atmos.cloud_scheme.atmos_coupling": {
            "values": [
                "atmosphere_radiation", 
                "atmosphere_microphysics_precipitation"
            ]
        }, 
        "cmip6.atmos.cloud_scheme.optical_cloud_properties.cloud_overlap_method": {
            "values": [
                "maximum-random: combination of maximum and random overlap between clouds"
            ]
        }, 
        "cmip6.atmos.cloud_scheme.sub_grid_scale_water_distribution.type": {
            "values": [
                "diagnostic"
            ]
        }, 
        "cmip6.atmos.cloud_scheme.sub_grid_scale_water_distribution.function_order": {
            "values": [
                2
            ]
        }, 
        "cmip6.atmos.cloud_scheme.sub_grid_scale_water_distribution.convection_coupling": {
            "values": [
                "coupled with deep", 
                "coupled with shallow"
            ]
        }, 
        "cmip6.atmos.cloud_scheme.sub_grid_scale_ice_distribution.type": {
            "values": [
                "diagnostic"
            ]
        }, 
        "cmip6.atmos.cloud_scheme.sub_grid_scale_ice_distribution.function_order": {
            "values": [
                2
            ]
        }, 
        "cmip6.atmos.gravity_waves.name": {
            "values": [
                "Gravity Wave Mountain Blocking"
            ]
        }, 
        "cmip6.atmos.gravity_waves.sponge_layer": {
            "values": [
                "Rayleigh friction"
            ]
        }, 
        "cmip6.atmos.gravity_waves.background": {
            "values": [
                "discrete spectrum"
            ]
        }, 
        "cmip6.atmos.gravity_waves.subgrid_scale_orography": {
            "values": [
                "effect on drag", 
                "effect on lifting", 
                "enhanced topography: To enhance the generation of long waves in the atmosphere"
            ]
        }, 
        "cmip6.atmos.gravity_waves.orographic_gravity_waves.name": {
            "values": [
                "Gravity Wave Mountain Blocking"
            ]
        }, 
        "cmip6.atmos.gravity_waves.orographic_gravity_waves.source_mechanisms": {
            "values": [
                "hydraulic jump", 
                "low level flow blocking", 
                "statistical sub-grid scale variance"
            ]
        }, 
        "cmip6.atmos.gravity_waves.orographic_gravity_waves.calculation_method": {
            "values": [
                "non-linear calculation", 
                "more than two cardinal directions"
            ]
        }, 
        "cmip6.atmos.gravity_waves.orographic_gravity_waves.propagation_scheme": {
            "values": [
                "non-linear theory"
            ]
        }, 
        "cmip6.atmos.gravity_waves.orographic_gravity_waves.dissipation_scheme": {
            "values": [
                "wave saturation vs Richardson number"
            ]
        }, 
        "cmip6.atmos.gravity_waves.non_orographic_gravity_waves.source_mechanisms": {
            "values": [
                "convection"
            ]
        }, 
        "cmip6.atmos.gravity_waves.non_orographic_gravity_waves.calculation_method": {
            "values": [
                "spatially dependent", 
                "temporally dependent"
            ]
        }, 
        "cmip6.atmos.gravity_waves.non_orographic_gravity_waves.propagation_scheme": {
            "values": [
                "non-linear theory"
            ]
        }, 
        "cmip6.atmos.natural_forcing.solar_pathways.pathways": {
            "values": [
                "SW radiation: Shortwave solar spectral irradiance."
            ]
        }, 
        "cmip6.atmos.natural_forcing.solar_constant.type": {
            "values": [
                "transient"
            ]
        }, 
        "cmip6.atmos.natural_forcing.solar_constant.transient_characteristics": {
            "values": [
                "1365.00"
            ]
        }, 
        "cmip6.atmos.natural_forcing.orbital_parameters.type": {
            "values": [
                "fixed"
            ]
        }, 
        "cmip6.atmos.natural_forcing.orbital_parameters.fixed_reference_date": {
            "values": [
                0
            ]
        }, 
        "cmip6.atmos.natural_forcing.orbital_parameters.computation_method": {
            "values": [
                "Berger 1978"
            ]
        }, 
        "cmip6.atmos.natural_forcing.insolation_ozone.solar_ozone_impact": {
            "values": [
                false
            ]
        }
    }
}